asm/__init__.py
asm/__main__.py
asm/alice_skills_manager.py
asm/exceptions.py
asm/skill_entry.py
asm/skill_repo.py
asm/skill_state.py
asm/util.py
alice_skills_manager-0.0.8.dist-info/METADATA
alice_skills_manager-0.0.8.dist-info/WHEEL
alice_skills_manager-0.0.8.dist-info/entry_points.txt
alice_skills_manager-0.0.8.dist-info/top_level.txt
alice_skills_manager-0.0.8.dist-info/RECORD
